mfd_ping/__init__.py
mfd_ping/base.py
mfd_ping/esxi.py
mfd_ping/exceptions.py
mfd_ping/freebsd.py
mfd_ping/linux.py
mfd_ping/mellanox.py
mfd_ping/windows.py
mfd_ping/traffics/__init__.py
mfd_ping/traffics/client_traffic.py
mfd_ping/traffics/server_traffic.py
mfd_ping-1.15.0.dist-info/licenses/AUTHORS.md
mfd_ping-1.15.0.dist-info/licenses/LICENSE.md
mfd_ping-1.15.0.dist-info/METADATA
mfd_ping-1.15.0.dist-info/WHEEL
mfd_ping-1.15.0.dist-info/top_level.txt
mfd_ping-1.15.0.dist-info/RECORD
