Metadata-Version: 2.4
Name: mfd-ping
Version: 1.15.0
Summary: Module for handling basic ping command operations over different operating systems for network diagnostic purposes.
Project-URL: Homepage, https://github.com/intel/mfd
Project-URL: Repository, https://github.com/intel/mfd-ping
Project-URL: Issues, https://github.com/intel/mfd-ping/issues
Project-URL: Changelog, https://github.com/intel/mfd-ping/blob/main/CHANGELOG.md
Requires-Python: <3.14,>=3.10
License-File: LICENSE.md
License-File: AUTHORS.md
Requires-Dist: mfd_common_libs>=1.11.0
Requires-Dist: mfd_kernel_namespace>=1.8.0
Requires-Dist: netaddr~=0.8.0
Requires-Dist: mfd-esxi<4,>=3.2.0
Requires-Dist: mfd-traffic-manager~=1.18
Requires-Dist: mfd-typing<2,>=1.23.0
Dynamic: license-file
